construction_meta_data_builder/__init__.py
construction_meta_data_builder/__main__.py
construction_meta_data_builder/_version.py
construction_meta_data_builder/freecad_exporter.py
construction_meta_data_builder/main.py
construction_meta_data_builder/py.typed
construction_meta_data_builder/readme_generator.py
construction_meta_data_builder/resources/img/no_image_available.png
construction_meta_data_builder/resources/img/origins.csv
construction_meta_data_builder/resources/scripts/freecad_export_image_script.py
construction_meta_data_builder/resources/templates/template_construction_readme.md.jinja
construction_meta_data_builder/resources/templates/template_workspace_readme.md.jinja
construction_meta_data_builder-0.0.1.dist-info/LICENSE
construction_meta_data_builder-0.0.1.dist-info/METADATA
construction_meta_data_builder-0.0.1.dist-info/WHEEL
construction_meta_data_builder-0.0.1.dist-info/entry_points.txt
construction_meta_data_builder-0.0.1.dist-info/top_level.txt
construction_meta_data_builder-0.0.1.dist-info/RECORD
