Metadata-Version: 2.1
Name: construction_meta_data_builder
Version: 0.0.1
Summary: README file generator for FreeCAD construction workspaces.
Home-page: https://github.com/twyleg/construction_meta_data_builder
Author: Torsten Wylegala
Author-email: mail@twyleg.de
License: GPL 3.0
Keywords: FreeCAD Export Constructions Generator
License-File: LICENSE
Requires-Dist: simple-python-app
Requires-Dist: jinja2 ~=3.1.4
